pyweatherlite/Base.py
pyweatherlite/__init__.py
pyweatherlite/helpers.py
pyweatherlite/index.py
pyweatherlite-0.1.0.dist-info/LICENSE
pyweatherlite-0.1.0.dist-info/METADATA
pyweatherlite-0.1.0.dist-info/WHEEL
pyweatherlite-0.1.0.dist-info/entry_points.txt
pyweatherlite-0.1.0.dist-info/top_level.txt
pyweatherlite-0.1.0.dist-info/RECORD
