Metadata-Version: 2.1
Name: pyweatherlite
Version: 0.1.0
Summary: A lightweight python library to extract weather data
Home-page: https://github.com/Terre8055/pyweatherlite
Author: Michael Appiah Dankwah
Author-email: michaelappiah2018@icloud.com
License: MIT
Platform: UNKNOWN
License-File: LICENSE
Requires-Dist: requests
